competency_api-0.4.0.dist-info/METADATA
competency_api-0.4.0.dist-info/WHEEL
competency_api/__init__.py
competency_api/competency_api.cpython-312-darwin.so
competency_api-0.4.0.dist-info/RECORD
